md_helper/__init__.py
md_helper/md_add_space.py
md_helper/md_update_url.py
md_helper/question_list.py
md_helper/standard-readme-django-cn.template
md_helper/templite.py
sample/__init__.py
sample/package_data.dat
sample/simple.py
zfind/__init__.py
zcommands_zx-0.0.3.dist-info/LICENSE.txt
zcommands_zx-0.0.3.dist-info/METADATA
zcommands_zx-0.0.3.dist-info/WHEEL
zcommands_zx-0.0.3.dist-info/entry_points.txt
zcommands_zx-0.0.3.dist-info/top_level.txt
zcommands_zx-0.0.3.dist-info/RECORD
