Metadata-Version: 2.1
Name: zcommands-zx
Version: 0.0.3
Summary: 使用python增强的shell命令
Home-page: UNKNOWN
Author: notfresh@github
Author-email: notfresh@foxmail.com
License: UNKNOWN
Project-URL: Bug Reports, https://github.com/notfresh/zcommands/issues
Project-URL: Funding, https://donate.pypi.org
Project-URL: Source, https://github.com/notfresh/zcommands/
Keywords: sample,setuptools,development
Platform: UNKNOWN
Classifier: Development Status :: 3 - Alpha
Classifier: Intended Audience :: Developers
Classifier: Topic :: Software Development :: Build Tools
Classifier: License :: OSI Approved :: MIT License
Classifier: Programming Language :: Python :: 3
Classifier: Programming Language :: Python :: 3.5
Classifier: Programming Language :: Python :: 3.6
Classifier: Programming Language :: Python :: 3.7
Classifier: Programming Language :: Python :: 3.8
Classifier: Programming Language :: Python :: 3 :: Only
Requires-Python: >=3.5, <4
Provides-Extra: dev
Requires-Dist: check-manifest ; extra == 'dev'
Provides-Extra: test
Requires-Dist: coverage ; extra == 'test'
